cpg_utils/__init__.py
cpg_utils/cloud.py
cpg_utils-2.1.1.dist-info/LICENSE
cpg_utils-2.1.1.dist-info/METADATA
cpg_utils-2.1.1.dist-info/WHEEL
cpg_utils-2.1.1.dist-info/top_level.txt
cpg_utils-2.1.1.dist-info/RECORD
