Metadata-Version: 2.1
Name: cpg-utils
Version: 2.1.1
Summary: Library of convenience functions specific to the CPG
Home-page: https://github.com/populationgenomics/cpg-utils
License: MIT
Keywords: bioinformatics
Platform: UNKNOWN
Classifier: Environment :: Console
Classifier: Intended Audience :: Science/Research
Classifier: License :: OSI Approved :: GNU General Public License v3 (GPLv3)
Classifier: Natural Language :: English
Classifier: Operating System :: MacOS :: MacOS X
Classifier: Operating System :: POSIX
Classifier: Operating System :: Unix
Classifier: Programming Language :: Python
Classifier: Topic :: Scientific/Engineering
Classifier: Topic :: Scientific/Engineering :: Bio-Informatics
License-File: LICENSE
